Metadata-Version: 2.1
Name: TSfraction
Version: 0.0.2
Summary: Fraction by Tarid Suwansri
Home-page: https://github.com/TaridSuwansri/TSfraction
Download-URL: https://github.com/TaridSuwansri/TSfraction/archive/v0.0.2.zip
Author: Tarid Suwansri
Author-email: taridsuwansri@gmail.com
License: MIT
Keywords: Fraction,Mathematics,Tarid,Suwansri
Classifier: Development Status :: 3 - Alpha
Classifier: Intended Audience :: Education
Classifier: Topic :: Utilities
Classifier: License :: OSI Approved :: MIT License
Classifier: Programming Language :: Python :: 3
Classifier: Programming Language :: Python :: 3.4
Classifier: Programming Language :: Python :: 3.5
Classifier: Programming Language :: Python :: 3.6
Classifier: Programming Language :: Python :: 3.7
Classifier: Programming Language :: Python :: 3.8
Classifier: Programming Language :: Python :: 3.9
Classifier: Programming Language :: Python :: 3.10
License-File: LICENSE.txt
